pyjas/__init__.py
pyjas/v1_1/__init__.py
pyjas/v1_1/content_negotiation.py
pyjas/v1_1/helper.py
pyjas/v1_1/jsonapi_builder.py
pyjas-0.2.3.dist-info/LICENSE
pyjas-0.2.3.dist-info/METADATA
pyjas-0.2.3.dist-info/WHEEL
pyjas-0.2.3.dist-info/RECORD
